indata/__init__.py
indata/dataio/__init__.py
indata/dataio/load.py
indata/dataio/transformer.py
indata/exception/__init__.py
indata/exception/base.py
indata/plot/__init__.py
indata/plot/boxplot.py
indata/plot/distribution.py
indata/plot/splom.py
indata/table/__init__.py
indata/table/dqt.py
indata/utils/__init__.py
indata/utils/checks.py
indata/utils/count.py
indata-1.1.1.dist-info/WHEEL
indata-1.1.1.dist-info/METADATA
indata-1.1.1.dist-info/RECORD
