Metadata-Version: 2.1
Name: indata
Version: 1.1.1
Summary: A tool in order to easily generate data quality reports from ABTs, visualize data and manipulate the ABT (analytics base table)
Home-page: https://github.com/RaphSku/indata
License: Apache-2.0
Keywords: data quality report,data science,data visualization,analytics base table
Author: RapSku
Author-email: rapsku.dev@gmail.com
Requires-Python: >=3.9,<4.0
Classifier: License :: OSI Approved :: Apache Software License
Classifier: Programming Language :: Python :: 3
Classifier: Programming Language :: Python :: 3.10
Classifier: Programming Language :: Python :: 3.9
Requires-Dist: attrs (>=22.1.0,<23.0.0)
Requires-Dist: numpy (>=1.22.3,<2.0.0)
Requires-Dist: pandas (>=1.4.2,<2.0.0)
Requires-Dist: plotly (>=5.7.0,<6.0.0)
Requires-Dist: tabulate (>=0.8.9,<0.9.0)
Project-URL: Repository, https://github.com/RaphSku/indata
